utils_devops/__init__.py
utils_devops/core/__init__.py
utils_devops/core/datetimes.py
utils_devops/core/envs.py
utils_devops/core/files.py
utils_devops/core/logs.py
utils_devops/core/script_helpers.py
utils_devops/core/strings.py
utils_devops/core/systems.py
utils_devops/extras/__init__.py
utils_devops/extras/aws_ops.py
utils_devops/extras/docker_ops.py
utils_devops/extras/git_ops.py
utils_devops/extras/interaction_ops.py
utils_devops/extras/metrics_ops.py
utils_devops/extras/network_ops.py
utils_devops/extras/nginx_ops.py
utils_devops/extras/notification_ops.py
utils_devops/extras/performance_ops.py
utils_devops/extras/ssh_ops.py
utils_devops/extras/vault_ops.py
utils_devops-0.1.174.dist-info/METADATA
utils_devops-0.1.174.dist-info/WHEEL
utils_devops-0.1.174.dist-info/entry_points.txt
utils_devops-0.1.174.dist-info/RECORD
